<?xml version="1.0" encoding="UTF-8"?>
<snippetsTree>
 <snippets file="./PMC6380980/results/word/frequencies/results.xml">
  <result title="frequency" word="acnes" count="107"/>
  <result title="frequency" word="bacteriophage" count="50"/>
  <result title="frequency" word="bacteriophages" count="50"/>
  <result title="frequency" word="phage" count="49"/>
  <result title="frequency" word="therapy" count="49"/>
  <result title="frequency" word="acne" count="48"/>
  <result title="frequency" word="resistance" count="44"/>
  <result title="frequency" word="skin" count="42"/>
  <result title="frequency" word="Propionibacterium" count="41"/>
  <result title="frequency" word="antibiotic" count="30"/>
  <result title="frequency" word="Dermatol" count="28"/>
  <result title="frequency" word="phages" count="27"/>
  <result title="frequency" word="human" count="26"/>
  <result title="frequency" word="antibiotics" count="23"/>
  <result title="frequency" word="bacteria" count="22"/>
 </snippets>
</snippetsTree>
