<?xml version="1.0" encoding="UTF-8"?>
<snippetsTree>
 <snippets file="essoil/PMC4566053/results/word/frequencies/results.xml">
  <result title="frequency" word="biochar" count="107"/>
  <result title="frequency" word="plants" count="94"/>
  <result title="frequency" word="F.C." count="93"/>
  <result title="frequency" word="gypsum" count="83"/>
  <result title="frequency" word="water" count="75"/>
  <result title="frequency" word="control" count="62"/>
  <result title="frequency" word="compared" count="58"/>
  <result title="frequency" word="stressed" count="52"/>
  <result title="frequency" word="soil" count="51"/>
  <result title="frequency" word="treatments" count="49"/>
  <result title="frequency" word="plant" count="39"/>
  <result title="frequency" word="rate" count="38"/>
  <result title="frequency" word="non-stressed" count="37"/>
  <result title="frequency" word="Plant" count="33"/>
  <result title="frequency" word="stress" count="33"/>
  <result title="frequency" word="stomatal" count="32"/>
  <result title="frequency" word="conductance" count="29"/>
  <result title="frequency" word="drought" count="28"/>
  <result title="frequency" word="increased" count="28"/>
  <result title="frequency" word="leaf" count="28"/>
  <result title="frequency" word="WUE" count="27"/>
  <result title="frequency" word="Comparison" count="26"/>
  <result title="frequency" word="conditions." count="26"/>
  <result title="frequency" word="treated" count="26"/>
  <result title="frequency" word="plants." count="25"/>
  <result title="frequency" word="Soil" count="24"/>
  <result title="frequency" word="area" count="24"/>
  <result title="frequency" word="observed" count="23"/>
  <result title="frequency" word="height" count="22"/>
  <result title="frequency" word="significant" count="22"/>
  <result title="frequency" word="Figure" count="21"/>
  <result title="frequency" word="combination" count="21"/>
  <result title="frequency" word="different" count="21"/>
 </snippets>
</snippetsTree>
