<?xml version="1.0" encoding="UTF-8"?>
<snippetsTree>
 <snippets file="essoil/PMC5101707/results/word/frequencies/results.xml">
  <result title="frequency" word="activity" count="30"/>
  <result title="frequency" word="(. ± ." count="26"/>
  <result title="frequency" word=". ± ." count="26"/>
  <result title="frequency" word="EOs" count="24"/>
  <result title="frequency" word="essential" count="23"/>
  <result title="frequency" word="μg/mL)," count="22"/>
 </snippets>
</snippetsTree>
