<?xml version="1.0" encoding="UTF-8" standalone="yes"?><responseWrapper xmlns:slx="http://www.scholix.org" xmlns:epmc="https://www.europepmc.org/data"><version>6.1</version><hitCount>1</hitCount><nextCursorMark>AoIIQALUzSgyMDkzMjY5OA==</nextCursorMark><request><query>10.1080/10412905.2007.9699228</query><resultType>lite</resultType><synonym>false</synonym><cursorMark>*</cursorMark><pageSize>25</pageSize><sort></sort></request><resultList><result><id>IND43895560</id><source>AGR</source><doi>10.1080/10412905.2007.9699228</doi><title>Essential oil analysis of Fuernrohria setifolia C. Koch from Iran.</title><authorString>Sonboli A, Salehi P, Vala MM.</authorString><journalTitle>Journal of essential oil research : JEOR.</journalTitle><issue>1</issue><journalVolume>19</journalVolume><pubYear>2007</pubYear><journalIssn>1041-2905</journalIssn><pageInfo>47-48</pageInfo><pubType>journal article</pubType><isOpenAccess>N</isOpenAccess><inEPMC>N</inEPMC><inPMC>N</inPMC><hasPDF>N</hasPDF><hasBook>N</hasBook><citedByCount>0</citedByCount><hasReferences>Y</hasReferences><hasTextMinedTerms>Y</hasTextMinedTerms><hasDbCrossReferences>N</hasDbCrossReferences><hasLabsLinks>N</hasLabsLinks><hasTMAccessionNumbers>N</hasTMAccessionNumbers><firstIndexDate>2007-10-02</firstIndexDate><firstPublicationDate>2007-01-01</firstPublicationDate></result></resultList></responseWrapper>