<?xml version="1.0" encoding="UTF-8" standalone="yes"?><responseWrapper xmlns:slx="http://www.scholix.org" xmlns:epmc="https://www.europepmc.org/data"><version>6.1</version><hitCount>1</hitCount><nextCursorMark>AoIIP7WN3CgyMDgxMjc5MQ==</nextCursorMark><request><query>10.1080/10412905.2000.9699568</query><resultType>lite</resultType><synonym>false</synonym><cursorMark>*</cursorMark><pageSize>25</pageSize><sort></sort></request><resultList><result><id>IND22064996</id><source>AGR</source><doi>10.1080/10412905.2000.9699568</doi><title>Essential oils of Glycosmis pentaphylla (Cor.). A new report from Assam, India.</title><authorString>Ahmed R, Choudhury S, Vajczikova I, Leclercq PA.</authorString><journalTitle>Journal of essential oil research : JEOR.</journalTitle><issue>4</issue><journalVolume>12</journalVolume><pubYear>2000</pubYear><journalIssn>1041-2905</journalIssn><pageInfo>471-474</pageInfo><pubType>journal article</pubType><isOpenAccess>N</isOpenAccess><inEPMC>N</inEPMC><inPMC>N</inPMC><hasPDF>N</hasPDF><hasBook>N</hasBook><citedByCount>1</citedByCount><hasReferences>Y</hasReferences><hasTextMinedTerms>Y</hasTextMinedTerms><hasDbCrossReferences>N</hasDbCrossReferences><hasLabsLinks>N</hasLabsLinks><hasTMAccessionNumbers>N</hasTMAccessionNumbers><firstIndexDate>2007-07-02</firstIndexDate><firstPublicationDate>2000-07-01</firstPublicationDate></result></resultList></responseWrapper>