<?xml version="1.0" encoding="UTF-8"?>
<results title="disease">
 <result pre="be a determining factor in various disorders such as acne," exact="atopic dermatitis," post="and psoriasis 4– 6 . The skin is a"/>
 <result pre="factor in various disorders such as acne, atopic dermatitis, and" exact="psoriasis" post="4– 6 . The skin is a critical barrier"/>
 <result pre="or lactating women, presence of any skin ailments (atopic dermatitis," exact="psoriasis" post="and stasis eczema), scar, inflammation or tattoos, which might"/>
 <result pre="affected by different microorganisms associated with skin disorders such as" exact="atopic dermatitis," post="acne vulgaris, psoriasis etc. 4, 6 . The skin"/>
 <result pre="different microorganisms associated with skin disorders such as atopic dermatitis," exact="acne vulgaris," post="psoriasis etc. 4, 6 . The skin surface varies"/>
 <result pre="associated with skin disorders such as atopic dermatitis, acne vulgaris," exact="psoriasis" post="etc. 4, 6 . The skin surface varies topographically"/>
 <result pre="associated with reduced immune response and skin diseases such as" exact="atopic dermatitis" post="and psoriasis 9, 51 . Higher levels of claudin-1"/>
 <result pre="with reduced immune response and skin diseases such as atopic" exact="dermatitis" post="and psoriasis 9, 51 . Higher levels of claudin-1"/>
 <result pre="immune response and skin diseases such as atopic dermatitis and" exact="psoriasis" post="9, 51 . Higher levels of claudin-1 in the"/>
 <result pre="Molecular characterization of the skin fungal microbiota in patients with" exact="seborrheic dermatitis" post="J. Clin. Exp. Dermatol. Res. 2014 5 1000239 33."/>
 <result pre="characterization of the skin fungal microbiota in patients with seborrheic" exact="dermatitis" post="J. Clin. Exp. Dermatol. Res. 2014 5 1000239 33."/>
 <result pre="A Takenouchi K Ito M Impaired water barrier function in" exact="acne vulgaris" post="Arch. Dermatol. Res. 1995 287 214 218 10.1007/BF01262335 7763094"/>
 <result pre="and sensitization to skin-associated microbial antigens in adult patients with" exact="atopic dermatitis" post="Int. J. Dermatol. 2014 53 27 33 10.1111/ijd.12198 23879225"/>
 <result pre="sensitization to skin-associated microbial antigens in adult patients with atopic" exact="dermatitis" post="Int. J. Dermatol. 2014 53 27 33 10.1111/ijd.12198 23879225"/>
</results>
